README.rst
pylint_mccabe.py
setup.py
pylint_mccabe.egg-info/PKG-INFO
pylint_mccabe.egg-info/SOURCES.txt
pylint_mccabe.egg-info/dependency_links.txt
pylint_mccabe.egg-info/requires.txt
pylint_mccabe.egg-info/top_level.txt