Metadata-Version: 1.0
Name: pylint-mccabe
Version: 0.1.3
Summary: McCabe complexity checker as a PyLint plugin
Home-page: http://pypi.python.org/pypi/pylint-mccabe/
Author: Infoxchange Australia dev team
Author-email: devs@infoxchange.net.au
License: MIT
Platform: UNKNOWN
